pdu/__init__.py
pdu/__main__.py
pdu/du.py
pdu-0.0.3.dist-info/METADATA
pdu-0.0.3.dist-info/RECORD
pdu-0.0.3.dist-info/WHEEL
pdu-0.0.3.dist-info/entry_points.txt
pdu-0.0.3.dist-info/top_level.txt
