Metadata-Version: 2.1
Name: pdu
Version: 0.0.3
Summary: Python Disk Usage
Home-page: https://github.com/tslight/pdu
Author: Toby Slight
Author-email: tobyslight@gmail.com
License: UNKNOWN
Platform: UNKNOWN
Classifier: Programming Language :: Python :: 3
Classifier: License :: OSI Approved :: ISC License (ISCL)
Classifier: Operating System :: OS Independent
